farseernmr/__init__.py
farseernmr-2.0.0.dev0.dist-info/AUTHORS.rst
farseernmr-2.0.0.dev0.dist-info/COPYING
farseernmr-2.0.0.dev0.dist-info/METADATA
farseernmr-2.0.0.dev0.dist-info/WHEEL
farseernmr-2.0.0.dev0.dist-info/entry_points.txt
farseernmr-2.0.0.dev0.dist-info/top_level.txt
farseernmr-2.0.0.dev0.dist-info/RECORD
