Metadata-Version: 2.1
Name: farseernmr
Version: 2.0.0.dev0
Summary: A software suite for automatic treatment, analysis and plotting of large and multivariable datasets of bioNMR peaklists.
Home-page: https://github.com/Farseer-NMR/FarSeer-NMR
Author: FarSeer-NMR
Author-email: farseer.nmr@gmail.com
License: GNU GPLv3+
Project-URL: Documentation, https://farseernmr.readthedocs.io/
Project-URL: Changelog, https://farseernmr.readthedocs.io/en/latest/changelog.html
Project-URL: Issue Tracker, https://github.com/FarSeer-NMR/FarSeer-NMR/issues
Keywords: Proteins,DNA,RNA,Structural Biology,Molecular Biology,Biochemistry,Nuclear Magnetic Resonance
Platform: UNKNOWN
Classifier: Development Status :: 1 - Planning
Classifier: Intended Audience :: Developers
Classifier: Intended Audience :: Education
Classifier: Intended Audience :: Science/Research
Classifier: Topic :: Scientific/Engineering :: Bio-Informatics
Classifier: Topic :: Scientific/Engineering :: Chemistry
Classifier: License :: OSI Approved :: GNU General Public License v2 (GPLv2)
Classifier: License :: OSI Approved :: GNU General Public License v3 or later (GPLv3+)
Classifier: Operating System :: Microsoft :: Windows
Classifier: Operating System :: MacOS
Classifier: Operating System :: Unix
Classifier: Operating System :: POSIX
Classifier: Environment :: Console
Classifier: Programming Language :: Python
Classifier: Programming Language :: Python :: 3
Classifier: Programming Language :: Python :: 3.6
Classifier: Programming Language :: Python :: 3.7
Classifier: Programming Language :: Python :: 3.8
Classifier: Topic :: Utilities
Requires-Python: >=3.6, <=3.9
Provides-Extra: sup
Requires-Dist: matplotlib (<4,>=3) ; extra == 'sup'
Requires-Dist: numpy (<2,>=1) ; extra == 'sup'
